ZtjDirModuleImport.py
py_ztj_dir_import-0.0.1.dist-info/METADATA
py_ztj_dir_import-0.0.1.dist-info/WHEEL
py_ztj_dir_import-0.0.1.dist-info/top_level.txt
py_ztj_dir_import-0.0.1.dist-info/RECORD
