Metadata-Version: 2.1
Name: py-ztj-dir-import
Version: 0.0.1
Summary: python directory module import package
Home-page: https://github.com/ztj1993/py-dir-import
Author: ZhangTianJie
Author-email: ztj1993@gmail.com
License: MIT License
Keywords: aria2 rpc client
Platform: UNKNOWN
